{
  "version": "3.2",
  "log": [
    {
      "ERC20": {
        "src": "@openzeppelin\\contracts\\token\\ERC20\\ERC20.sol:35",
        "version": {
          "withMetadata": "7165ea78945608218190603307fd2387ba83b7043b2e2c4b0ac3145fad81dd4d",
          "withoutMetadata": "446af738423993bbf37b968e84db4f492fe60237dac4f87e185949ac5cf5dad2",
          "linkedWithoutMetadata": "446af738423993bbf37b968e84db4f492fe60237dac4f87e185949ac5cf5dad2"
        },
        "inherit": [
          "IERC20Metadata",
          "IERC20",
          "Context"
        ],
        "libraries": [],
        "methods": [
          "(string,string)",
          "name()",
          "symbol()",
          "decimals()",
          "totalSupply()",
          "balanceOf(address)",
          "transfer(address,uint256)",
          "allowance(address,address)",
          "approve(address,uint256)",
          "transferFrom(address,address,uint256)",
          "increaseAllowance(address,uint256)",
          "decreaseAllowance(address,uint256)"
        ],
        "linkReferences": [],
        "errors": [
          {
            "kind": "constructor",
            "contract": "ERC20",
            "src": "@openzeppelin\\contracts\\token\\ERC20\\ERC20.sol:54"
          }
        ],
        "layout": {
          "storage": [
            {
              "contract": "ERC20",
              "label": "_balances",
              "type": "t_mapping(t_address,t_uint256)",
              "src": "@openzeppelin\\contracts\\token\\ERC20\\ERC20.sol:36"
            },
            {
              "contract": "ERC20",
              "label": "_allowances",
              "type": "t_mapping(t_address,t_mapping(t_address,t_uint256))",
              "src": "@openzeppelin\\contracts\\token\\ERC20\\ERC20.sol:38"
            },
            {
              "contract": "ERC20",
              "label": "_totalSupply",
              "type": "t_uint256",
              "src": "@openzeppelin\\contracts\\token\\ERC20\\ERC20.sol:40"
            },
            {
              "contract": "ERC20",
              "label": "_name",
              "type": "t_string_storage",
              "src": "@openzeppelin\\contracts\\token\\ERC20\\ERC20.sol:42"
            },
            {
              "contract": "ERC20",
              "label": "_symbol",
              "type": "t_string_storage",
              "src": "@openzeppelin\\contracts\\token\\ERC20\\ERC20.sol:43"
            }
          ],
          "types": {
            "t_mapping(t_address,t_uint256)": {
              "label": "mapping(address => uint256)"
            },
            "t_address": {
              "label": "address"
            },
            "t_uint256": {
              "label": "uint256"
            },
            "t_mapping(t_address,t_mapping(t_address,t_uint256))": {
              "label": "mapping(address => mapping(address => uint256))"
            },
            "t_string_storage": {
              "label": "string"
            }
          },
          "layoutVersion": "1.1"
        }
      },
      "IERC20": {
        "src": "@openzeppelin\\contracts\\token\\ERC20\\IERC20.sol:9",
        "inherit": [],
        "libraries": [],
        "methods": [
          "totalSupply()",
          "balanceOf(address)",
          "transfer(address,uint256)",
          "allowance(address,address)",
          "approve(address,uint256)",
          "transferFrom(address,address,uint256)"
        ],
        "linkReferences": [],
        "errors": [],
        "layout": {
          "storage": [],
          "types": {},
          "layoutVersion": "1.1"
        }
      },
      "IERC20Metadata": {
        "src": "@openzeppelin\\contracts\\token\\ERC20\\extensions\\IERC20Metadata.sol:13",
        "inherit": [
          "IERC20"
        ],
        "libraries": [],
        "methods": [
          "name()",
          "symbol()",
          "decimals()"
        ],
        "linkReferences": [],
        "errors": [],
        "layout": {
          "storage": [],
          "types": {},
          "layoutVersion": "1.1"
        }
      },
      "Context": {
        "src": "@openzeppelin\\contracts\\utils\\Context.sol:16",
        "inherit": [],
        "libraries": [],
        "methods": [],
        "linkReferences": [],
        "errors": [],
        "layout": {
          "storage": [],
          "types": {},
          "layoutVersion": "1.1"
        }
      },
      "POTATToken": {
        "src": "contracts\\main.sol:6",
        "version": {
          "withMetadata": "436bc46677f47058fdf0debb5d9bfb4b3071fc5f00dd5eb6c7236cc9ad307168",
          "withoutMetadata": "1af1cb9c5f1532c9c29c43a87beeb8ec29bb57828e11cdf8e0272fd3dc57981b",
          "linkedWithoutMetadata": "1af1cb9c5f1532c9c29c43a87beeb8ec29bb57828e11cdf8e0272fd3dc57981b"
        },
        "inherit": [
          "ERC20",
          "IERC20Metadata",
          "IERC20",
          "Context"
        ],
        "libraries": [],
        "methods": [
          "()",
          "buying()",
          "automatedDistribution()",
          "transfer(address,uint256)",
          "transferFrom(address,address,uint256)",
          "redeemExpiredTokens()",
          "()",
          "()"
        ],
        "linkReferences": [],
        "errors": [
          {
            "kind": "constructor",
            "contract": "POTATToken",
            "src": "contracts\\main.sol:10"
          }
        ],
        "layout": {
          "storage": [
            {
              "contract": "POTATToken",
              "label": "owner",
              "type": "t_address",
              "src": "contracts\\main.sol:7"
            },
            {
              "contract": "POTATToken",
              "label": "purchaseTimestamps",
              "type": "t_mapping(t_address,t_uint256)",
              "src": "contracts\\main.sol:8"
            }
          ],
          "types": {
            "t_address": {
              "label": "address"
            },
            "t_mapping(t_address,t_uint256)": {
              "label": "mapping(address => uint256)"
            },
            "t_uint256": {
              "label": "uint256"
            }
          },
          "layoutVersion": "1.1"
        }
      }
    },
    {
      "ERC20": {
        "src": "@openzeppelin\\contracts\\token\\ERC20\\ERC20.sol:35",
        "version": {
          "withMetadata": "7165ea78945608218190603307fd2387ba83b7043b2e2c4b0ac3145fad81dd4d",
          "withoutMetadata": "446af738423993bbf37b968e84db4f492fe60237dac4f87e185949ac5cf5dad2",
          "linkedWithoutMetadata": "446af738423993bbf37b968e84db4f492fe60237dac4f87e185949ac5cf5dad2"
        },
        "inherit": [
          "IERC20Metadata",
          "IERC20",
          "Context"
        ],
        "libraries": [],
        "methods": [
          "(string,string)",
          "name()",
          "symbol()",
          "decimals()",
          "totalSupply()",
          "balanceOf(address)",
          "transfer(address,uint256)",
          "allowance(address,address)",
          "approve(address,uint256)",
          "transferFrom(address,address,uint256)",
          "increaseAllowance(address,uint256)",
          "decreaseAllowance(address,uint256)"
        ],
        "linkReferences": [],
        "errors": [
          {
            "kind": "constructor",
            "contract": "ERC20",
            "src": "@openzeppelin\\contracts\\token\\ERC20\\ERC20.sol:54"
          }
        ],
        "layout": {
          "storage": [
            {
              "contract": "ERC20",
              "label": "_balances",
              "type": "t_mapping(t_address,t_uint256)",
              "src": "@openzeppelin\\contracts\\token\\ERC20\\ERC20.sol:36"
            },
            {
              "contract": "ERC20",
              "label": "_allowances",
              "type": "t_mapping(t_address,t_mapping(t_address,t_uint256))",
              "src": "@openzeppelin\\contracts\\token\\ERC20\\ERC20.sol:38"
            },
            {
              "contract": "ERC20",
              "label": "_totalSupply",
              "type": "t_uint256",
              "src": "@openzeppelin\\contracts\\token\\ERC20\\ERC20.sol:40"
            },
            {
              "contract": "ERC20",
              "label": "_name",
              "type": "t_string_storage",
              "src": "@openzeppelin\\contracts\\token\\ERC20\\ERC20.sol:42"
            },
            {
              "contract": "ERC20",
              "label": "_symbol",
              "type": "t_string_storage",
              "src": "@openzeppelin\\contracts\\token\\ERC20\\ERC20.sol:43"
            }
          ],
          "types": {
            "t_mapping(t_address,t_uint256)": {
              "label": "mapping(address => uint256)"
            },
            "t_address": {
              "label": "address"
            },
            "t_uint256": {
              "label": "uint256"
            },
            "t_mapping(t_address,t_mapping(t_address,t_uint256))": {
              "label": "mapping(address => mapping(address => uint256))"
            },
            "t_string_storage": {
              "label": "string"
            }
          },
          "layoutVersion": "1.1"
        }
      },
      "IERC20": {
        "src": "@openzeppelin\\contracts\\token\\ERC20\\IERC20.sol:9",
        "inherit": [],
        "libraries": [],
        "methods": [
          "totalSupply()",
          "balanceOf(address)",
          "transfer(address,uint256)",
          "allowance(address,address)",
          "approve(address,uint256)",
          "transferFrom(address,address,uint256)"
        ],
        "linkReferences": [],
        "errors": [],
        "layout": {
          "storage": [],
          "types": {},
          "layoutVersion": "1.1"
        }
      },
      "IERC20Metadata": {
        "src": "@openzeppelin\\contracts\\token\\ERC20\\extensions\\IERC20Metadata.sol:13",
        "inherit": [
          "IERC20"
        ],
        "libraries": [],
        "methods": [
          "name()",
          "symbol()",
          "decimals()"
        ],
        "linkReferences": [],
        "errors": [],
        "layout": {
          "storage": [],
          "types": {},
          "layoutVersion": "1.1"
        }
      },
      "Context": {
        "src": "@openzeppelin\\contracts\\utils\\Context.sol:16",
        "inherit": [],
        "libraries": [],
        "methods": [],
        "linkReferences": [],
        "errors": [],
        "layout": {
          "storage": [],
          "types": {},
          "layoutVersion": "1.1"
        }
      },
      "POTATToken": {
        "src": "contracts\\main.sol:6",
        "version": {
          "withMetadata": "a7e17d0501b53e5e930ad3d2d96c5a724f12bd838e4ce36af81e5ad182d18831",
          "withoutMetadata": "1af1cb9c5f1532c9c29c43a87beeb8ec29bb57828e11cdf8e0272fd3dc57981b",
          "linkedWithoutMetadata": "1af1cb9c5f1532c9c29c43a87beeb8ec29bb57828e11cdf8e0272fd3dc57981b"
        },
        "inherit": [
          "ERC20",
          "IERC20Metadata",
          "IERC20",
          "Context"
        ],
        "libraries": [],
        "methods": [
          "()",
          "buying()",
          "automatedDistribution()",
          "transfer(address,uint256)",
          "transferFrom(address,address,uint256)",
          "redeemExpiredTokens()",
          "()",
          "()"
        ],
        "linkReferences": [],
        "errors": [
          {
            "kind": "constructor",
            "contract": "POTATToken",
            "src": "contracts\\main.sol:10"
          }
        ],
        "layout": {
          "storage": [
            {
              "contract": "POTATToken",
              "label": "owner",
              "type": "t_address",
              "src": "contracts\\main.sol:7"
            },
            {
              "contract": "POTATToken",
              "label": "purchaseTimestamps",
              "type": "t_mapping(t_address,t_uint256)",
              "src": "contracts\\main.sol:8"
            }
          ],
          "types": {
            "t_address": {
              "label": "address"
            },
            "t_mapping(t_address,t_uint256)": {
              "label": "mapping(address => uint256)"
            },
            "t_uint256": {
              "label": "uint256"
            }
          },
          "layoutVersion": "1.1"
        }
      }
    },
    {
      "ERC20": {
        "src": "@openzeppelin\\contracts\\token\\ERC20\\ERC20.sol:35",
        "version": {
          "withMetadata": "7165ea78945608218190603307fd2387ba83b7043b2e2c4b0ac3145fad81dd4d",
          "withoutMetadata": "446af738423993bbf37b968e84db4f492fe60237dac4f87e185949ac5cf5dad2",
          "linkedWithoutMetadata": "446af738423993bbf37b968e84db4f492fe60237dac4f87e185949ac5cf5dad2"
        },
        "inherit": [
          "IERC20Metadata",
          "IERC20",
          "Context"
        ],
        "libraries": [],
        "methods": [
          "(string,string)",
          "name()",
          "symbol()",
          "decimals()",
          "totalSupply()",
          "balanceOf(address)",
          "transfer(address,uint256)",
          "allowance(address,address)",
          "approve(address,uint256)",
          "transferFrom(address,address,uint256)",
          "increaseAllowance(address,uint256)",
          "decreaseAllowance(address,uint256)"
        ],
        "linkReferences": [],
        "errors": [
          {
            "kind": "constructor",
            "contract": "ERC20",
            "src": "@openzeppelin\\contracts\\token\\ERC20\\ERC20.sol:54"
          }
        ],
        "layout": {
          "storage": [
            {
              "contract": "ERC20",
              "label": "_balances",
              "type": "t_mapping(t_address,t_uint256)",
              "src": "@openzeppelin\\contracts\\token\\ERC20\\ERC20.sol:36"
            },
            {
              "contract": "ERC20",
              "label": "_allowances",
              "type": "t_mapping(t_address,t_mapping(t_address,t_uint256))",
              "src": "@openzeppelin\\contracts\\token\\ERC20\\ERC20.sol:38"
            },
            {
              "contract": "ERC20",
              "label": "_totalSupply",
              "type": "t_uint256",
              "src": "@openzeppelin\\contracts\\token\\ERC20\\ERC20.sol:40"
            },
            {
              "contract": "ERC20",
              "label": "_name",
              "type": "t_string_storage",
              "src": "@openzeppelin\\contracts\\token\\ERC20\\ERC20.sol:42"
            },
            {
              "contract": "ERC20",
              "label": "_symbol",
              "type": "t_string_storage",
              "src": "@openzeppelin\\contracts\\token\\ERC20\\ERC20.sol:43"
            }
          ],
          "types": {
            "t_mapping(t_address,t_uint256)": {
              "label": "mapping(address => uint256)"
            },
            "t_address": {
              "label": "address"
            },
            "t_uint256": {
              "label": "uint256"
            },
            "t_mapping(t_address,t_mapping(t_address,t_uint256))": {
              "label": "mapping(address => mapping(address => uint256))"
            },
            "t_string_storage": {
              "label": "string"
            }
          },
          "layoutVersion": "1.1"
        }
      },
      "IERC20": {
        "src": "@openzeppelin\\contracts\\token\\ERC20\\IERC20.sol:9",
        "inherit": [],
        "libraries": [],
        "methods": [
          "totalSupply()",
          "balanceOf(address)",
          "transfer(address,uint256)",
          "allowance(address,address)",
          "approve(address,uint256)",
          "transferFrom(address,address,uint256)"
        ],
        "linkReferences": [],
        "errors": [],
        "layout": {
          "storage": [],
          "types": {},
          "layoutVersion": "1.1"
        }
      },
      "IERC20Metadata": {
        "src": "@openzeppelin\\contracts\\token\\ERC20\\extensions\\IERC20Metadata.sol:13",
        "inherit": [
          "IERC20"
        ],
        "libraries": [],
        "methods": [
          "name()",
          "symbol()",
          "decimals()"
        ],
        "linkReferences": [],
        "errors": [],
        "layout": {
          "storage": [],
          "types": {},
          "layoutVersion": "1.1"
        }
      },
      "Context": {
        "src": "@openzeppelin\\contracts\\utils\\Context.sol:16",
        "inherit": [],
        "libraries": [],
        "methods": [],
        "linkReferences": [],
        "errors": [],
        "layout": {
          "storage": [],
          "types": {},
          "layoutVersion": "1.1"
        }
      },
      "POTATToken": {
        "src": "contracts\\main.sol:6",
        "version": {
          "withMetadata": "44686b4b65626848e7bb02ba8e4ade4cb68d56e689d0b5a485d00e95eb306b52",
          "withoutMetadata": "d02154815d8f47b3fbe9e87205ae6c04a009d787d859585529b3143b16b1c6b1",
          "linkedWithoutMetadata": "d02154815d8f47b3fbe9e87205ae6c04a009d787d859585529b3143b16b1c6b1"
        },
        "inherit": [
          "ERC20",
          "IERC20Metadata",
          "IERC20",
          "Context"
        ],
        "libraries": [],
        "methods": [
          "()",
          "buying()",
          "automatedDistribution()",
          "transfer(address,uint256)",
          "transferFrom(address,address,uint256)",
          "redeemExpiredTokens()",
          "()",
          "()"
        ],
        "linkReferences": [],
        "errors": [
          {
            "kind": "constructor",
            "contract": "POTATToken",
            "src": "contracts\\main.sol:10"
          }
        ],
        "layout": {
          "storage": [
            {
              "contract": "POTATToken",
              "label": "owner",
              "type": "t_address",
              "src": "contracts\\main.sol:7"
            },
            {
              "contract": "POTATToken",
              "label": "purchaseTimestamps",
              "type": "t_mapping(t_address,t_uint256)",
              "src": "contracts\\main.sol:8"
            }
          ],
          "types": {
            "t_address": {
              "label": "address"
            },
            "t_mapping(t_address,t_uint256)": {
              "label": "mapping(address => uint256)"
            },
            "t_uint256": {
              "label": "uint256"
            }
          },
          "layoutVersion": "1.1"
        }
      }
    },
    {
      "ERC20": {
        "src": "@openzeppelin\\contracts\\token\\ERC20\\ERC20.sol:35",
        "version": {
          "withMetadata": "7165ea78945608218190603307fd2387ba83b7043b2e2c4b0ac3145fad81dd4d",
          "withoutMetadata": "446af738423993bbf37b968e84db4f492fe60237dac4f87e185949ac5cf5dad2",
          "linkedWithoutMetadata": "446af738423993bbf37b968e84db4f492fe60237dac4f87e185949ac5cf5dad2"
        },
        "inherit": [
          "IERC20Metadata",
          "IERC20",
          "Context"
        ],
        "libraries": [],
        "methods": [
          "(string,string)",
          "name()",
          "symbol()",
          "decimals()",
          "totalSupply()",
          "balanceOf(address)",
          "transfer(address,uint256)",
          "allowance(address,address)",
          "approve(address,uint256)",
          "transferFrom(address,address,uint256)",
          "increaseAllowance(address,uint256)",
          "decreaseAllowance(address,uint256)"
        ],
        "linkReferences": [],
        "errors": [
          {
            "kind": "constructor",
            "contract": "ERC20",
            "src": "@openzeppelin\\contracts\\token\\ERC20\\ERC20.sol:54"
          }
        ],
        "layout": {
          "storage": [
            {
              "contract": "ERC20",
              "label": "_balances",
              "type": "t_mapping(t_address,t_uint256)",
              "src": "@openzeppelin\\contracts\\token\\ERC20\\ERC20.sol:36"
            },
            {
              "contract": "ERC20",
              "label": "_allowances",
              "type": "t_mapping(t_address,t_mapping(t_address,t_uint256))",
              "src": "@openzeppelin\\contracts\\token\\ERC20\\ERC20.sol:38"
            },
            {
              "contract": "ERC20",
              "label": "_totalSupply",
              "type": "t_uint256",
              "src": "@openzeppelin\\contracts\\token\\ERC20\\ERC20.sol:40"
            },
            {
              "contract": "ERC20",
              "label": "_name",
              "type": "t_string_storage",
              "src": "@openzeppelin\\contracts\\token\\ERC20\\ERC20.sol:42"
            },
            {
              "contract": "ERC20",
              "label": "_symbol",
              "type": "t_string_storage",
              "src": "@openzeppelin\\contracts\\token\\ERC20\\ERC20.sol:43"
            }
          ],
          "types": {
            "t_mapping(t_address,t_uint256)": {
              "label": "mapping(address => uint256)"
            },
            "t_address": {
              "label": "address"
            },
            "t_uint256": {
              "label": "uint256"
            },
            "t_mapping(t_address,t_mapping(t_address,t_uint256))": {
              "label": "mapping(address => mapping(address => uint256))"
            },
            "t_string_storage": {
              "label": "string"
            }
          },
          "layoutVersion": "1.1"
        }
      },
      "IERC20": {
        "src": "@openzeppelin\\contracts\\token\\ERC20\\IERC20.sol:9",
        "inherit": [],
        "libraries": [],
        "methods": [
          "totalSupply()",
          "balanceOf(address)",
          "transfer(address,uint256)",
          "allowance(address,address)",
          "approve(address,uint256)",
          "transferFrom(address,address,uint256)"
        ],
        "linkReferences": [],
        "errors": [],
        "layout": {
          "storage": [],
          "types": {},
          "layoutVersion": "1.1"
        }
      },
      "IERC20Metadata": {
        "src": "@openzeppelin\\contracts\\token\\ERC20\\extensions\\IERC20Metadata.sol:13",
        "inherit": [
          "IERC20"
        ],
        "libraries": [],
        "methods": [
          "name()",
          "symbol()",
          "decimals()"
        ],
        "linkReferences": [],
        "errors": [],
        "layout": {
          "storage": [],
          "types": {},
          "layoutVersion": "1.1"
        }
      },
      "Context": {
        "src": "@openzeppelin\\contracts\\utils\\Context.sol:16",
        "inherit": [],
        "libraries": [],
        "methods": [],
        "linkReferences": [],
        "errors": [],
        "layout": {
          "storage": [],
          "types": {},
          "layoutVersion": "1.1"
        }
      },
      "POTATToken": {
        "src": "contracts\\main.sol:6",
        "version": {
          "withMetadata": "44686b4b65626848e7bb02ba8e4ade4cb68d56e689d0b5a485d00e95eb306b52",
          "withoutMetadata": "d02154815d8f47b3fbe9e87205ae6c04a009d787d859585529b3143b16b1c6b1",
          "linkedWithoutMetadata": "d02154815d8f47b3fbe9e87205ae6c04a009d787d859585529b3143b16b1c6b1"
        },
        "inherit": [
          "ERC20",
          "IERC20Metadata",
          "IERC20",
          "Context"
        ],
        "libraries": [],
        "methods": [
          "()",
          "buying()",
          "automatedDistribution()",
          "transfer(address,uint256)",
          "transferFrom(address,address,uint256)",
          "redeemExpiredTokens()",
          "()",
          "()"
        ],
        "linkReferences": [],
        "errors": [
          {
            "kind": "constructor",
            "contract": "POTATToken",
            "src": "contracts\\main.sol:10"
          }
        ],
        "layout": {
          "storage": [
            {
              "contract": "POTATToken",
              "label": "owner",
              "type": "t_address",
              "src": "contracts\\main.sol:7"
            },
            {
              "contract": "POTATToken",
              "label": "purchaseTimestamps",
              "type": "t_mapping(t_address,t_uint256)",
              "src": "contracts\\main.sol:8"
            }
          ],
          "types": {
            "t_address": {
              "label": "address"
            },
            "t_mapping(t_address,t_uint256)": {
              "label": "mapping(address => uint256)"
            },
            "t_uint256": {
              "label": "uint256"
            }
          },
          "layoutVersion": "1.1"
        }
      }
    },
    {
      "ERC20": {
        "src": "@openzeppelin\\contracts\\token\\ERC20\\ERC20.sol:35",
        "version": {
          "withMetadata": "7165ea78945608218190603307fd2387ba83b7043b2e2c4b0ac3145fad81dd4d",
          "withoutMetadata": "446af738423993bbf37b968e84db4f492fe60237dac4f87e185949ac5cf5dad2",
          "linkedWithoutMetadata": "446af738423993bbf37b968e84db4f492fe60237dac4f87e185949ac5cf5dad2"
        },
        "inherit": [
          "IERC20Metadata",
          "IERC20",
          "Context"
        ],
        "libraries": [],
        "methods": [
          "(string,string)",
          "name()",
          "symbol()",
          "decimals()",
          "totalSupply()",
          "balanceOf(address)",
          "transfer(address,uint256)",
          "allowance(address,address)",
          "approve(address,uint256)",
          "transferFrom(address,address,uint256)",
          "increaseAllowance(address,uint256)",
          "decreaseAllowance(address,uint256)"
        ],
        "linkReferences": [],
        "errors": [
          {
            "kind": "constructor",
            "contract": "ERC20",
            "src": "@openzeppelin\\contracts\\token\\ERC20\\ERC20.sol:54"
          }
        ],
        "layout": {
          "storage": [
            {
              "contract": "ERC20",
              "label": "_balances",
              "type": "t_mapping(t_address,t_uint256)",
              "src": "@openzeppelin\\contracts\\token\\ERC20\\ERC20.sol:36"
            },
            {
              "contract": "ERC20",
              "label": "_allowances",
              "type": "t_mapping(t_address,t_mapping(t_address,t_uint256))",
              "src": "@openzeppelin\\contracts\\token\\ERC20\\ERC20.sol:38"
            },
            {
              "contract": "ERC20",
              "label": "_totalSupply",
              "type": "t_uint256",
              "src": "@openzeppelin\\contracts\\token\\ERC20\\ERC20.sol:40"
            },
            {
              "contract": "ERC20",
              "label": "_name",
              "type": "t_string_storage",
              "src": "@openzeppelin\\contracts\\token\\ERC20\\ERC20.sol:42"
            },
            {
              "contract": "ERC20",
              "label": "_symbol",
              "type": "t_string_storage",
              "src": "@openzeppelin\\contracts\\token\\ERC20\\ERC20.sol:43"
            }
          ],
          "types": {
            "t_mapping(t_address,t_uint256)": {
              "label": "mapping(address => uint256)"
            },
            "t_address": {
              "label": "address"
            },
            "t_uint256": {
              "label": "uint256"
            },
            "t_mapping(t_address,t_mapping(t_address,t_uint256))": {
              "label": "mapping(address => mapping(address => uint256))"
            },
            "t_string_storage": {
              "label": "string"
            }
          },
          "layoutVersion": "1.1"
        }
      },
      "IERC20": {
        "src": "@openzeppelin\\contracts\\token\\ERC20\\IERC20.sol:9",
        "inherit": [],
        "libraries": [],
        "methods": [
          "totalSupply()",
          "balanceOf(address)",
          "transfer(address,uint256)",
          "allowance(address,address)",
          "approve(address,uint256)",
          "transferFrom(address,address,uint256)"
        ],
        "linkReferences": [],
        "errors": [],
        "layout": {
          "storage": [],
          "types": {},
          "layoutVersion": "1.1"
        }
      },
      "IERC20Metadata": {
        "src": "@openzeppelin\\contracts\\token\\ERC20\\extensions\\IERC20Metadata.sol:13",
        "inherit": [
          "IERC20"
        ],
        "libraries": [],
        "methods": [
          "name()",
          "symbol()",
          "decimals()"
        ],
        "linkReferences": [],
        "errors": [],
        "layout": {
          "storage": [],
          "types": {},
          "layoutVersion": "1.1"
        }
      },
      "Context": {
        "src": "@openzeppelin\\contracts\\utils\\Context.sol:16",
        "inherit": [],
        "libraries": [],
        "methods": [],
        "linkReferences": [],
        "errors": [],
        "layout": {
          "storage": [],
          "types": {},
          "layoutVersion": "1.1"
        }
      },
      "POTATToken": {
        "src": "contracts\\main.sol:6",
        "version": {
          "withMetadata": "decf1b32a3d8d60e1e757b7e2f332bfd863338415e211229c4adda13777beb94",
          "withoutMetadata": "69abb2f79b3c26ecac8a5fecc84d56eae09469390d20c0c2023748c106496abf",
          "linkedWithoutMetadata": "69abb2f79b3c26ecac8a5fecc84d56eae09469390d20c0c2023748c106496abf"
        },
        "inherit": [
          "ERC20",
          "IERC20Metadata",
          "IERC20",
          "Context"
        ],
        "libraries": [],
        "methods": [
          "()",
          "buying()",
          "automatedDistribution()",
          "transfer(address,uint256)",
          "transferFrom(address,address,uint256)",
          "redeemExpiredTokens()",
          "()",
          "()"
        ],
        "linkReferences": [],
        "errors": [
          {
            "kind": "constructor",
            "contract": "POTATToken",
            "src": "contracts\\main.sol:10"
          }
        ],
        "layout": {
          "storage": [
            {
              "contract": "POTATToken",
              "label": "owner",
              "type": "t_address",
              "src": "contracts\\main.sol:7"
            },
            {
              "contract": "POTATToken",
              "label": "purchaseTimestamps",
              "type": "t_mapping(t_address,t_uint256)",
              "src": "contracts\\main.sol:8"
            }
          ],
          "types": {
            "t_address": {
              "label": "address"
            },
            "t_mapping(t_address,t_uint256)": {
              "label": "mapping(address => uint256)"
            },
            "t_uint256": {
              "label": "uint256"
            }
          },
          "layoutVersion": "1.1"
        }
      }
    },
    {
      "ERC20": {
        "src": "@openzeppelin\\contracts\\token\\ERC20\\ERC20.sol:35",
        "version": {
          "withMetadata": "7165ea78945608218190603307fd2387ba83b7043b2e2c4b0ac3145fad81dd4d",
          "withoutMetadata": "446af738423993bbf37b968e84db4f492fe60237dac4f87e185949ac5cf5dad2",
          "linkedWithoutMetadata": "446af738423993bbf37b968e84db4f492fe60237dac4f87e185949ac5cf5dad2"
        },
        "inherit": [
          "IERC20Metadata",
          "IERC20",
          "Context"
        ],
        "libraries": [],
        "methods": [
          "(string,string)",
          "name()",
          "symbol()",
          "decimals()",
          "totalSupply()",
          "balanceOf(address)",
          "transfer(address,uint256)",
          "allowance(address,address)",
          "approve(address,uint256)",
          "transferFrom(address,address,uint256)",
          "increaseAllowance(address,uint256)",
          "decreaseAllowance(address,uint256)"
        ],
        "linkReferences": [],
        "errors": [
          {
            "kind": "constructor",
            "contract": "ERC20",
            "src": "@openzeppelin\\contracts\\token\\ERC20\\ERC20.sol:54"
          }
        ],
        "layout": {
          "storage": [
            {
              "contract": "ERC20",
              "label": "_balances",
              "type": "t_mapping(t_address,t_uint256)",
              "src": "@openzeppelin\\contracts\\token\\ERC20\\ERC20.sol:36"
            },
            {
              "contract": "ERC20",
              "label": "_allowances",
              "type": "t_mapping(t_address,t_mapping(t_address,t_uint256))",
              "src": "@openzeppelin\\contracts\\token\\ERC20\\ERC20.sol:38"
            },
            {
              "contract": "ERC20",
              "label": "_totalSupply",
              "type": "t_uint256",
              "src": "@openzeppelin\\contracts\\token\\ERC20\\ERC20.sol:40"
            },
            {
              "contract": "ERC20",
              "label": "_name",
              "type": "t_string_storage",
              "src": "@openzeppelin\\contracts\\token\\ERC20\\ERC20.sol:42"
            },
            {
              "contract": "ERC20",
              "label": "_symbol",
              "type": "t_string_storage",
              "src": "@openzeppelin\\contracts\\token\\ERC20\\ERC20.sol:43"
            }
          ],
          "types": {
            "t_mapping(t_address,t_uint256)": {
              "label": "mapping(address => uint256)"
            },
            "t_address": {
              "label": "address"
            },
            "t_uint256": {
              "label": "uint256"
            },
            "t_mapping(t_address,t_mapping(t_address,t_uint256))": {
              "label": "mapping(address => mapping(address => uint256))"
            },
            "t_string_storage": {
              "label": "string"
            }
          },
          "layoutVersion": "1.1"
        }
      },
      "IERC20": {
        "src": "@openzeppelin\\contracts\\token\\ERC20\\IERC20.sol:9",
        "inherit": [],
        "libraries": [],
        "methods": [
          "totalSupply()",
          "balanceOf(address)",
          "transfer(address,uint256)",
          "allowance(address,address)",
          "approve(address,uint256)",
          "transferFrom(address,address,uint256)"
        ],
        "linkReferences": [],
        "errors": [],
        "layout": {
          "storage": [],
          "types": {},
          "layoutVersion": "1.1"
        }
      },
      "IERC20Metadata": {
        "src": "@openzeppelin\\contracts\\token\\ERC20\\extensions\\IERC20Metadata.sol:13",
        "inherit": [
          "IERC20"
        ],
        "libraries": [],
        "methods": [
          "name()",
          "symbol()",
          "decimals()"
        ],
        "linkReferences": [],
        "errors": [],
        "layout": {
          "storage": [],
          "types": {},
          "layoutVersion": "1.1"
        }
      },
      "Context": {
        "src": "@openzeppelin\\contracts\\utils\\Context.sol:16",
        "inherit": [],
        "libraries": [],
        "methods": [],
        "linkReferences": [],
        "errors": [],
        "layout": {
          "storage": [],
          "types": {},
          "layoutVersion": "1.1"
        }
      },
      "POTATToken": {
        "src": "contracts\\main.sol:6",
        "version": {
          "withMetadata": "6c1c8980adf0394cd2fd56faca6c2de241e7142fe8b56770c2f262f3a1d63ec4",
          "withoutMetadata": "52e98f430f45d679e28512e8919f2d26682c266a09029a6974034ea78c3043f5",
          "linkedWithoutMetadata": "52e98f430f45d679e28512e8919f2d26682c266a09029a6974034ea78c3043f5"
        },
        "inherit": [
          "ERC20",
          "IERC20Metadata",
          "IERC20",
          "Context"
        ],
        "libraries": [],
        "methods": [
          "()",
          "buying()",
          "transfer(address,uint256)",
          "transferFrom(address,address,uint256)",
          "redeemExpiredTokens()",
          "()",
          "()"
        ],
        "linkReferences": [],
        "errors": [
          {
            "kind": "constructor",
            "contract": "POTATToken",
            "src": "contracts\\main.sol:10"
          }
        ],
        "layout": {
          "storage": [
            {
              "contract": "POTATToken",
              "label": "owner",
              "type": "t_address",
              "src": "contracts\\main.sol:7"
            },
            {
              "contract": "POTATToken",
              "label": "purchaseTimestamps",
              "type": "t_mapping(t_address,t_uint256)",
              "src": "contracts\\main.sol:8"
            }
          ],
          "types": {
            "t_address": {
              "label": "address"
            },
            "t_mapping(t_address,t_uint256)": {
              "label": "mapping(address => uint256)"
            },
            "t_uint256": {
              "label": "uint256"
            }
          },
          "layoutVersion": "1.1"
        }
      }
    },
    {
      "ERC20": {
        "src": "@openzeppelin\\contracts\\token\\ERC20\\ERC20.sol:35",
        "version": {
          "withMetadata": "7165ea78945608218190603307fd2387ba83b7043b2e2c4b0ac3145fad81dd4d",
          "withoutMetadata": "446af738423993bbf37b968e84db4f492fe60237dac4f87e185949ac5cf5dad2",
          "linkedWithoutMetadata": "446af738423993bbf37b968e84db4f492fe60237dac4f87e185949ac5cf5dad2"
        },
        "inherit": [
          "IERC20Metadata",
          "IERC20",
          "Context"
        ],
        "libraries": [],
        "methods": [
          "(string,string)",
          "name()",
          "symbol()",
          "decimals()",
          "totalSupply()",
          "balanceOf(address)",
          "transfer(address,uint256)",
          "allowance(address,address)",
          "approve(address,uint256)",
          "transferFrom(address,address,uint256)",
          "increaseAllowance(address,uint256)",
          "decreaseAllowance(address,uint256)"
        ],
        "linkReferences": [],
        "errors": [
          {
            "kind": "constructor",
            "contract": "ERC20",
            "src": "@openzeppelin\\contracts\\token\\ERC20\\ERC20.sol:54"
          }
        ],
        "layout": {
          "storage": [
            {
              "contract": "ERC20",
              "label": "_balances",
              "type": "t_mapping(t_address,t_uint256)",
              "src": "@openzeppelin\\contracts\\token\\ERC20\\ERC20.sol:36"
            },
            {
              "contract": "ERC20",
              "label": "_allowances",
              "type": "t_mapping(t_address,t_mapping(t_address,t_uint256))",
              "src": "@openzeppelin\\contracts\\token\\ERC20\\ERC20.sol:38"
            },
            {
              "contract": "ERC20",
              "label": "_totalSupply",
              "type": "t_uint256",
              "src": "@openzeppelin\\contracts\\token\\ERC20\\ERC20.sol:40"
            },
            {
              "contract": "ERC20",
              "label": "_name",
              "type": "t_string_storage",
              "src": "@openzeppelin\\contracts\\token\\ERC20\\ERC20.sol:42"
            },
            {
              "contract": "ERC20",
              "label": "_symbol",
              "type": "t_string_storage",
              "src": "@openzeppelin\\contracts\\token\\ERC20\\ERC20.sol:43"
            }
          ],
          "types": {
            "t_mapping(t_address,t_uint256)": {
              "label": "mapping(address => uint256)"
            },
            "t_address": {
              "label": "address"
            },
            "t_uint256": {
              "label": "uint256"
            },
            "t_mapping(t_address,t_mapping(t_address,t_uint256))": {
              "label": "mapping(address => mapping(address => uint256))"
            },
            "t_string_storage": {
              "label": "string"
            }
          },
          "layoutVersion": "1.1"
        }
      },
      "IERC20": {
        "src": "@openzeppelin\\contracts\\token\\ERC20\\IERC20.sol:9",
        "inherit": [],
        "libraries": [],
        "methods": [
          "totalSupply()",
          "balanceOf(address)",
          "transfer(address,uint256)",
          "allowance(address,address)",
          "approve(address,uint256)",
          "transferFrom(address,address,uint256)"
        ],
        "linkReferences": [],
        "errors": [],
        "layout": {
          "storage": [],
          "types": {},
          "layoutVersion": "1.1"
        }
      },
      "IERC20Metadata": {
        "src": "@openzeppelin\\contracts\\token\\ERC20\\extensions\\IERC20Metadata.sol:13",
        "inherit": [
          "IERC20"
        ],
        "libraries": [],
        "methods": [
          "name()",
          "symbol()",
          "decimals()"
        ],
        "linkReferences": [],
        "errors": [],
        "layout": {
          "storage": [],
          "types": {},
          "layoutVersion": "1.1"
        }
      },
      "Context": {
        "src": "@openzeppelin\\contracts\\utils\\Context.sol:16",
        "inherit": [],
        "libraries": [],
        "methods": [],
        "linkReferences": [],
        "errors": [],
        "layout": {
          "storage": [],
          "types": {},
          "layoutVersion": "1.1"
        }
      },
      "POTATToken": {
        "src": "contracts\\main.sol:6",
        "version": {
          "withMetadata": "6c1c8980adf0394cd2fd56faca6c2de241e7142fe8b56770c2f262f3a1d63ec4",
          "withoutMetadata": "52e98f430f45d679e28512e8919f2d26682c266a09029a6974034ea78c3043f5",
          "linkedWithoutMetadata": "52e98f430f45d679e28512e8919f2d26682c266a09029a6974034ea78c3043f5"
        },
        "inherit": [
          "ERC20",
          "IERC20Metadata",
          "IERC20",
          "Context"
        ],
        "libraries": [],
        "methods": [
          "()",
          "buying()",
          "transfer(address,uint256)",
          "transferFrom(address,address,uint256)",
          "redeemExpiredTokens()",
          "()",
          "()"
        ],
        "linkReferences": [],
        "errors": [
          {
            "kind": "constructor",
            "contract": "POTATToken",
            "src": "contracts\\main.sol:10"
          }
        ],
        "layout": {
          "storage": [
            {
              "contract": "POTATToken",
              "label": "owner",
              "type": "t_address",
              "src": "contracts\\main.sol:7"
            },
            {
              "contract": "POTATToken",
              "label": "purchaseTimestamps",
              "type": "t_mapping(t_address,t_uint256)",
              "src": "contracts\\main.sol:8"
            }
          ],
          "types": {
            "t_address": {
              "label": "address"
            },
            "t_mapping(t_address,t_uint256)": {
              "label": "mapping(address => uint256)"
            },
            "t_uint256": {
              "label": "uint256"
            }
          },
          "layoutVersion": "1.1"
        }
      }
    },
    {
      "ERC20": {
        "src": "@openzeppelin\\contracts\\token\\ERC20\\ERC20.sol:35",
        "version": {
          "withMetadata": "7165ea78945608218190603307fd2387ba83b7043b2e2c4b0ac3145fad81dd4d",
          "withoutMetadata": "446af738423993bbf37b968e84db4f492fe60237dac4f87e185949ac5cf5dad2",
          "linkedWithoutMetadata": "446af738423993bbf37b968e84db4f492fe60237dac4f87e185949ac5cf5dad2"
        },
        "inherit": [
          "IERC20Metadata",
          "IERC20",
          "Context"
        ],
        "libraries": [],
        "methods": [
          "(string,string)",
          "name()",
          "symbol()",
          "decimals()",
          "totalSupply()",
          "balanceOf(address)",
          "transfer(address,uint256)",
          "allowance(address,address)",
          "approve(address,uint256)",
          "transferFrom(address,address,uint256)",
          "increaseAllowance(address,uint256)",
          "decreaseAllowance(address,uint256)"
        ],
        "linkReferences": [],
        "errors": [
          {
            "kind": "constructor",
            "contract": "ERC20",
            "src": "@openzeppelin\\contracts\\token\\ERC20\\ERC20.sol:54"
          }
        ],
        "layout": {
          "storage": [
            {
              "contract": "ERC20",
              "label": "_balances",
              "type": "t_mapping(t_address,t_uint256)",
              "src": "@openzeppelin\\contracts\\token\\ERC20\\ERC20.sol:36"
            },
            {
              "contract": "ERC20",
              "label": "_allowances",
              "type": "t_mapping(t_address,t_mapping(t_address,t_uint256))",
              "src": "@openzeppelin\\contracts\\token\\ERC20\\ERC20.sol:38"
            },
            {
              "contract": "ERC20",
              "label": "_totalSupply",
              "type": "t_uint256",
              "src": "@openzeppelin\\contracts\\token\\ERC20\\ERC20.sol:40"
            },
            {
              "contract": "ERC20",
              "label": "_name",
              "type": "t_string_storage",
              "src": "@openzeppelin\\contracts\\token\\ERC20\\ERC20.sol:42"
            },
            {
              "contract": "ERC20",
              "label": "_symbol",
              "type": "t_string_storage",
              "src": "@openzeppelin\\contracts\\token\\ERC20\\ERC20.sol:43"
            }
          ],
          "types": {
            "t_mapping(t_address,t_uint256)": {
              "label": "mapping(address => uint256)"
            },
            "t_address": {
              "label": "address"
            },
            "t_uint256": {
              "label": "uint256"
            },
            "t_mapping(t_address,t_mapping(t_address,t_uint256))": {
              "label": "mapping(address => mapping(address => uint256))"
            },
            "t_string_storage": {
              "label": "string"
            }
          },
          "layoutVersion": "1.1"
        }
      },
      "IERC20": {
        "src": "@openzeppelin\\contracts\\token\\ERC20\\IERC20.sol:9",
        "inherit": [],
        "libraries": [],
        "methods": [
          "totalSupply()",
          "balanceOf(address)",
          "transfer(address,uint256)",
          "allowance(address,address)",
          "approve(address,uint256)",
          "transferFrom(address,address,uint256)"
        ],
        "linkReferences": [],
        "errors": [],
        "layout": {
          "storage": [],
          "types": {},
          "layoutVersion": "1.1"
        }
      },
      "IERC20Metadata": {
        "src": "@openzeppelin\\contracts\\token\\ERC20\\extensions\\IERC20Metadata.sol:13",
        "inherit": [
          "IERC20"
        ],
        "libraries": [],
        "methods": [
          "name()",
          "symbol()",
          "decimals()"
        ],
        "linkReferences": [],
        "errors": [],
        "layout": {
          "storage": [],
          "types": {},
          "layoutVersion": "1.1"
        }
      },
      "Context": {
        "src": "@openzeppelin\\contracts\\utils\\Context.sol:16",
        "inherit": [],
        "libraries": [],
        "methods": [],
        "linkReferences": [],
        "errors": [],
        "layout": {
          "storage": [],
          "types": {},
          "layoutVersion": "1.1"
        }
      },
      "POTATToken": {
        "src": "contracts\\main.sol:5",
        "version": {
          "withMetadata": "560322a480c2b7a6f9fa2540ffbd0168374ab67639e652e43ec41f50b1fed456",
          "withoutMetadata": "8609b66c243f57a22692451bd513ca6e4b85974ce13df017e7909b33d10bd468",
          "linkedWithoutMetadata": "8609b66c243f57a22692451bd513ca6e4b85974ce13df017e7909b33d10bd468"
        },
        "inherit": [
          "ERC20",
          "IERC20Metadata",
          "IERC20",
          "Context"
        ],
        "libraries": [],
        "methods": [
          "()",
          "buying()",
          "()",
          "()"
        ],
        "linkReferences": [],
        "errors": [
          {
            "kind": "constructor",
            "contract": "POTATToken",
            "src": "contracts\\main.sol:16"
          }
        ],
        "layout": {
          "storage": [
            {
              "contract": "POTATToken",
              "label": "owner",
              "type": "t_address",
              "src": "contracts\\main.sol:6"
            },
            {
              "contract": "POTATToken",
              "label": "purchaseTimestamps",
              "type": "t_mapping(t_address,t_uint256)",
              "src": "contracts\\main.sol:7"
            }
          ],
          "types": {
            "t_address": {
              "label": "address"
            },
            "t_mapping(t_address,t_uint256)": {
              "label": "mapping(address => uint256)"
            },
            "t_uint256": {
              "label": "uint256"
            }
          },
          "layoutVersion": "1.1"
        }
      }
    },
    {
      "ERC20": {
        "src": "@openzeppelin\\contracts\\token\\ERC20\\ERC20.sol:35",
        "version": {
          "withMetadata": "7165ea78945608218190603307fd2387ba83b7043b2e2c4b0ac3145fad81dd4d",
          "withoutMetadata": "446af738423993bbf37b968e84db4f492fe60237dac4f87e185949ac5cf5dad2",
          "linkedWithoutMetadata": "446af738423993bbf37b968e84db4f492fe60237dac4f87e185949ac5cf5dad2"
        },
        "inherit": [
          "IERC20Metadata",
          "IERC20",
          "Context"
        ],
        "libraries": [],
        "methods": [
          "(string,string)",
          "name()",
          "symbol()",
          "decimals()",
          "totalSupply()",
          "balanceOf(address)",
          "transfer(address,uint256)",
          "allowance(address,address)",
          "approve(address,uint256)",
          "transferFrom(address,address,uint256)",
          "increaseAllowance(address,uint256)",
          "decreaseAllowance(address,uint256)"
        ],
        "linkReferences": [],
        "errors": [
          {
            "kind": "constructor",
            "contract": "ERC20",
            "src": "@openzeppelin\\contracts\\token\\ERC20\\ERC20.sol:54"
          }
        ],
        "layout": {
          "storage": [
            {
              "contract": "ERC20",
              "label": "_balances",
              "type": "t_mapping(t_address,t_uint256)",
              "src": "@openzeppelin\\contracts\\token\\ERC20\\ERC20.sol:36"
            },
            {
              "contract": "ERC20",
              "label": "_allowances",
              "type": "t_mapping(t_address,t_mapping(t_address,t_uint256))",
              "src": "@openzeppelin\\contracts\\token\\ERC20\\ERC20.sol:38"
            },
            {
              "contract": "ERC20",
              "label": "_totalSupply",
              "type": "t_uint256",
              "src": "@openzeppelin\\contracts\\token\\ERC20\\ERC20.sol:40"
            },
            {
              "contract": "ERC20",
              "label": "_name",
              "type": "t_string_storage",
              "src": "@openzeppelin\\contracts\\token\\ERC20\\ERC20.sol:42"
            },
            {
              "contract": "ERC20",
              "label": "_symbol",
              "type": "t_string_storage",
              "src": "@openzeppelin\\contracts\\token\\ERC20\\ERC20.sol:43"
            }
          ],
          "types": {
            "t_mapping(t_address,t_uint256)": {
              "label": "mapping(address => uint256)"
            },
            "t_address": {
              "label": "address"
            },
            "t_uint256": {
              "label": "uint256"
            },
            "t_mapping(t_address,t_mapping(t_address,t_uint256))": {
              "label": "mapping(address => mapping(address => uint256))"
            },
            "t_string_storage": {
              "label": "string"
            }
          },
          "layoutVersion": "1.1"
        }
      },
      "IERC20": {
        "src": "@openzeppelin\\contracts\\token\\ERC20\\IERC20.sol:9",
        "inherit": [],
        "libraries": [],
        "methods": [
          "totalSupply()",
          "balanceOf(address)",
          "transfer(address,uint256)",
          "allowance(address,address)",
          "approve(address,uint256)",
          "transferFrom(address,address,uint256)"
        ],
        "linkReferences": [],
        "errors": [],
        "layout": {
          "storage": [],
          "types": {},
          "layoutVersion": "1.1"
        }
      },
      "IERC20Metadata": {
        "src": "@openzeppelin\\contracts\\token\\ERC20\\extensions\\IERC20Metadata.sol:13",
        "inherit": [
          "IERC20"
        ],
        "libraries": [],
        "methods": [
          "name()",
          "symbol()",
          "decimals()"
        ],
        "linkReferences": [],
        "errors": [],
        "layout": {
          "storage": [],
          "types": {},
          "layoutVersion": "1.1"
        }
      },
      "Context": {
        "src": "@openzeppelin\\contracts\\utils\\Context.sol:16",
        "inherit": [],
        "libraries": [],
        "methods": [],
        "linkReferences": [],
        "errors": [],
        "layout": {
          "storage": [],
          "types": {},
          "layoutVersion": "1.1"
        }
      },
      "POTATToken": {
        "src": "contracts\\main.sol:5",
        "version": {
          "withMetadata": "4d9fd2743396fa8aab0343baf00dd5a450aa382a7b9d82a005b86753326d897f",
          "withoutMetadata": "9c2565335fd42f812627c49bcbb06bb2070ba23f7e760fba8e083b455ed5a20f",
          "linkedWithoutMetadata": "9c2565335fd42f812627c49bcbb06bb2070ba23f7e760fba8e083b455ed5a20f"
        },
        "inherit": [
          "ERC20",
          "IERC20Metadata",
          "IERC20",
          "Context"
        ],
        "libraries": [],
        "methods": [
          "()",
          "buying()",
          "()",
          "()"
        ],
        "linkReferences": [],
        "errors": [
          {
            "kind": "constructor",
            "contract": "POTATToken",
            "src": "contracts\\main.sol:15"
          }
        ],
        "layout": {
          "storage": [
            {
              "contract": "POTATToken",
              "label": "owner",
              "type": "t_address",
              "src": "contracts\\main.sol:6"
            }
          ],
          "types": {
            "t_address": {
              "label": "address"
            }
          },
          "layoutVersion": "1.1"
        }
      }
    },
    {
      "ERC20": {
        "src": "@openzeppelin\\contracts\\token\\ERC20\\ERC20.sol:35",
        "version": {
          "withMetadata": "7165ea78945608218190603307fd2387ba83b7043b2e2c4b0ac3145fad81dd4d",
          "withoutMetadata": "446af738423993bbf37b968e84db4f492fe60237dac4f87e185949ac5cf5dad2",
          "linkedWithoutMetadata": "446af738423993bbf37b968e84db4f492fe60237dac4f87e185949ac5cf5dad2"
        },
        "inherit": [
          "IERC20Metadata",
          "IERC20",
          "Context"
        ],
        "libraries": [],
        "methods": [
          "(string,string)",
          "name()",
          "symbol()",
          "decimals()",
          "totalSupply()",
          "balanceOf(address)",
          "transfer(address,uint256)",
          "allowance(address,address)",
          "approve(address,uint256)",
          "transferFrom(address,address,uint256)",
          "increaseAllowance(address,uint256)",
          "decreaseAllowance(address,uint256)"
        ],
        "linkReferences": [],
        "errors": [
          {
            "kind": "constructor",
            "contract": "ERC20",
            "src": "@openzeppelin\\contracts\\token\\ERC20\\ERC20.sol:54"
          }
        ],
        "layout": {
          "storage": [
            {
              "contract": "ERC20",
              "label": "_balances",
              "type": "t_mapping(t_address,t_uint256)",
              "src": "@openzeppelin\\contracts\\token\\ERC20\\ERC20.sol:36"
            },
            {
              "contract": "ERC20",
              "label": "_allowances",
              "type": "t_mapping(t_address,t_mapping(t_address,t_uint256))",
              "src": "@openzeppelin\\contracts\\token\\ERC20\\ERC20.sol:38"
            },
            {
              "contract": "ERC20",
              "label": "_totalSupply",
              "type": "t_uint256",
              "src": "@openzeppelin\\contracts\\token\\ERC20\\ERC20.sol:40"
            },
            {
              "contract": "ERC20",
              "label": "_name",
              "type": "t_string_storage",
              "src": "@openzeppelin\\contracts\\token\\ERC20\\ERC20.sol:42"
            },
            {
              "contract": "ERC20",
              "label": "_symbol",
              "type": "t_string_storage",
              "src": "@openzeppelin\\contracts\\token\\ERC20\\ERC20.sol:43"
            }
          ],
          "types": {
            "t_mapping(t_address,t_uint256)": {
              "label": "mapping(address => uint256)"
            },
            "t_address": {
              "label": "address"
            },
            "t_uint256": {
              "label": "uint256"
            },
            "t_mapping(t_address,t_mapping(t_address,t_uint256))": {
              "label": "mapping(address => mapping(address => uint256))"
            },
            "t_string_storage": {
              "label": "string"
            }
          },
          "layoutVersion": "1.1"
        }
      },
      "IERC20": {
        "src": "@openzeppelin\\contracts\\token\\ERC20\\IERC20.sol:9",
        "inherit": [],
        "libraries": [],
        "methods": [
          "totalSupply()",
          "balanceOf(address)",
          "transfer(address,uint256)",
          "allowance(address,address)",
          "approve(address,uint256)",
          "transferFrom(address,address,uint256)"
        ],
        "linkReferences": [],
        "errors": [],
        "layout": {
          "storage": [],
          "types": {},
          "layoutVersion": "1.1"
        }
      },
      "IERC20Metadata": {
        "src": "@openzeppelin\\contracts\\token\\ERC20\\extensions\\IERC20Metadata.sol:13",
        "inherit": [
          "IERC20"
        ],
        "libraries": [],
        "methods": [
          "name()",
          "symbol()",
          "decimals()"
        ],
        "linkReferences": [],
        "errors": [],
        "layout": {
          "storage": [],
          "types": {},
          "layoutVersion": "1.1"
        }
      },
      "Context": {
        "src": "@openzeppelin\\contracts\\utils\\Context.sol:16",
        "inherit": [],
        "libraries": [],
        "methods": [],
        "linkReferences": [],
        "errors": [],
        "layout": {
          "storage": [],
          "types": {},
          "layoutVersion": "1.1"
        }
      },
      "POTATToken": {
        "src": "contracts\\main.sol:5",
        "version": {
          "withMetadata": "4d9fd2743396fa8aab0343baf00dd5a450aa382a7b9d82a005b86753326d897f",
          "withoutMetadata": "9c2565335fd42f812627c49bcbb06bb2070ba23f7e760fba8e083b455ed5a20f",
          "linkedWithoutMetadata": "9c2565335fd42f812627c49bcbb06bb2070ba23f7e760fba8e083b455ed5a20f"
        },
        "inherit": [
          "ERC20",
          "IERC20Metadata",
          "IERC20",
          "Context"
        ],
        "libraries": [],
        "methods": [
          "()",
          "buying()",
          "()",
          "()"
        ],
        "linkReferences": [],
        "errors": [
          {
            "kind": "constructor",
            "contract": "POTATToken",
            "src": "contracts\\main.sol:15"
          }
        ],
        "layout": {
          "storage": [
            {
              "contract": "POTATToken",
              "label": "owner",
              "type": "t_address",
              "src": "contracts\\main.sol:6"
            }
          ],
          "types": {
            "t_address": {
              "label": "address"
            }
          },
          "layoutVersion": "1.1"
        }
      }
    },
    {
      "ERC20": {
        "src": "@openzeppelin\\contracts\\token\\ERC20\\ERC20.sol:35",
        "version": {
          "withMetadata": "7165ea78945608218190603307fd2387ba83b7043b2e2c4b0ac3145fad81dd4d",
          "withoutMetadata": "446af738423993bbf37b968e84db4f492fe60237dac4f87e185949ac5cf5dad2",
          "linkedWithoutMetadata": "446af738423993bbf37b968e84db4f492fe60237dac4f87e185949ac5cf5dad2"
        },
        "inherit": [
          "IERC20Metadata",
          "IERC20",
          "Context"
        ],
        "libraries": [],
        "methods": [
          "(string,string)",
          "name()",
          "symbol()",
          "decimals()",
          "totalSupply()",
          "balanceOf(address)",
          "transfer(address,uint256)",
          "allowance(address,address)",
          "approve(address,uint256)",
          "transferFrom(address,address,uint256)",
          "increaseAllowance(address,uint256)",
          "decreaseAllowance(address,uint256)"
        ],
        "linkReferences": [],
        "errors": [
          {
            "kind": "constructor",
            "contract": "ERC20",
            "src": "@openzeppelin\\contracts\\token\\ERC20\\ERC20.sol:54"
          }
        ],
        "layout": {
          "storage": [
            {
              "contract": "ERC20",
              "label": "_balances",
              "type": "t_mapping(t_address,t_uint256)",
              "src": "@openzeppelin\\contracts\\token\\ERC20\\ERC20.sol:36"
            },
            {
              "contract": "ERC20",
              "label": "_allowances",
              "type": "t_mapping(t_address,t_mapping(t_address,t_uint256))",
              "src": "@openzeppelin\\contracts\\token\\ERC20\\ERC20.sol:38"
            },
            {
              "contract": "ERC20",
              "label": "_totalSupply",
              "type": "t_uint256",
              "src": "@openzeppelin\\contracts\\token\\ERC20\\ERC20.sol:40"
            },
            {
              "contract": "ERC20",
              "label": "_name",
              "type": "t_string_storage",
              "src": "@openzeppelin\\contracts\\token\\ERC20\\ERC20.sol:42"
            },
            {
              "contract": "ERC20",
              "label": "_symbol",
              "type": "t_string_storage",
              "src": "@openzeppelin\\contracts\\token\\ERC20\\ERC20.sol:43"
            }
          ],
          "types": {
            "t_mapping(t_address,t_uint256)": {
              "label": "mapping(address => uint256)"
            },
            "t_address": {
              "label": "address"
            },
            "t_uint256": {
              "label": "uint256"
            },
            "t_mapping(t_address,t_mapping(t_address,t_uint256))": {
              "label": "mapping(address => mapping(address => uint256))"
            },
            "t_string_storage": {
              "label": "string"
            }
          },
          "layoutVersion": "1.1"
        }
      },
      "IERC20": {
        "src": "@openzeppelin\\contracts\\token\\ERC20\\IERC20.sol:9",
        "inherit": [],
        "libraries": [],
        "methods": [
          "totalSupply()",
          "balanceOf(address)",
          "transfer(address,uint256)",
          "allowance(address,address)",
          "approve(address,uint256)",
          "transferFrom(address,address,uint256)"
        ],
        "linkReferences": [],
        "errors": [],
        "layout": {
          "storage": [],
          "types": {},
          "layoutVersion": "1.1"
        }
      },
      "IERC20Metadata": {
        "src": "@openzeppelin\\contracts\\token\\ERC20\\extensions\\IERC20Metadata.sol:13",
        "inherit": [
          "IERC20"
        ],
        "libraries": [],
        "methods": [
          "name()",
          "symbol()",
          "decimals()"
        ],
        "linkReferences": [],
        "errors": [],
        "layout": {
          "storage": [],
          "types": {},
          "layoutVersion": "1.1"
        }
      },
      "Context": {
        "src": "@openzeppelin\\contracts\\utils\\Context.sol:16",
        "inherit": [],
        "libraries": [],
        "methods": [],
        "linkReferences": [],
        "errors": [],
        "layout": {
          "storage": [],
          "types": {},
          "layoutVersion": "1.1"
        }
      },
      "POTATToken": {
        "src": "contracts\\main.sol:5",
        "version": {
          "withMetadata": "b3874874855b8f059a81a6ae3418aea7bd0a17864272e6ae03857d399f367b05",
          "withoutMetadata": "333a199d454e16244e96d2ee42bb55e9ce4fb2ec9c7bf9b3ecda2b8c5500081b",
          "linkedWithoutMetadata": "333a199d454e16244e96d2ee42bb55e9ce4fb2ec9c7bf9b3ecda2b8c5500081b"
        },
        "inherit": [
          "ERC20",
          "IERC20Metadata",
          "IERC20",
          "Context"
        ],
        "libraries": [],
        "methods": [
          "()",
          "buying()",
          "()",
          "()"
        ],
        "linkReferences": [],
        "errors": [
          {
            "kind": "constructor",
            "contract": "POTATToken",
            "src": "contracts\\main.sol:15"
          }
        ],
        "layout": {
          "storage": [
            {
              "contract": "POTATToken",
              "label": "owner",
              "type": "t_address",
              "src": "contracts\\main.sol:6"
            }
          ],
          "types": {
            "t_address": {
              "label": "address"
            }
          },
          "layoutVersion": "1.1"
        }
      }
    },
    {
      "ERC20": {
        "src": "@openzeppelin\\contracts\\token\\ERC20\\ERC20.sol:35",
        "version": {
          "withMetadata": "7165ea78945608218190603307fd2387ba83b7043b2e2c4b0ac3145fad81dd4d",
          "withoutMetadata": "446af738423993bbf37b968e84db4f492fe60237dac4f87e185949ac5cf5dad2",
          "linkedWithoutMetadata": "446af738423993bbf37b968e84db4f492fe60237dac4f87e185949ac5cf5dad2"
        },
        "inherit": [
          "IERC20Metadata",
          "IERC20",
          "Context"
        ],
        "libraries": [],
        "methods": [
          "(string,string)",
          "name()",
          "symbol()",
          "decimals()",
          "totalSupply()",
          "balanceOf(address)",
          "transfer(address,uint256)",
          "allowance(address,address)",
          "approve(address,uint256)",
          "transferFrom(address,address,uint256)",
          "increaseAllowance(address,uint256)",
          "decreaseAllowance(address,uint256)"
        ],
        "linkReferences": [],
        "errors": [
          {
            "kind": "constructor",
            "contract": "ERC20",
            "src": "@openzeppelin\\contracts\\token\\ERC20\\ERC20.sol:54"
          }
        ],
        "layout": {
          "storage": [
            {
              "contract": "ERC20",
              "label": "_balances",
              "type": "t_mapping(t_address,t_uint256)",
              "src": "@openzeppelin\\contracts\\token\\ERC20\\ERC20.sol:36"
            },
            {
              "contract": "ERC20",
              "label": "_allowances",
              "type": "t_mapping(t_address,t_mapping(t_address,t_uint256))",
              "src": "@openzeppelin\\contracts\\token\\ERC20\\ERC20.sol:38"
            },
            {
              "contract": "ERC20",
              "label": "_totalSupply",
              "type": "t_uint256",
              "src": "@openzeppelin\\contracts\\token\\ERC20\\ERC20.sol:40"
            },
            {
              "contract": "ERC20",
              "label": "_name",
              "type": "t_string_storage",
              "src": "@openzeppelin\\contracts\\token\\ERC20\\ERC20.sol:42"
            },
            {
              "contract": "ERC20",
              "label": "_symbol",
              "type": "t_string_storage",
              "src": "@openzeppelin\\contracts\\token\\ERC20\\ERC20.sol:43"
            }
          ],
          "types": {
            "t_mapping(t_address,t_uint256)": {
              "label": "mapping(address => uint256)"
            },
            "t_address": {
              "label": "address"
            },
            "t_uint256": {
              "label": "uint256"
            },
            "t_mapping(t_address,t_mapping(t_address,t_uint256))": {
              "label": "mapping(address => mapping(address => uint256))"
            },
            "t_string_storage": {
              "label": "string"
            }
          },
          "layoutVersion": "1.1"
        }
      },
      "IERC20": {
        "src": "@openzeppelin\\contracts\\token\\ERC20\\IERC20.sol:9",
        "inherit": [],
        "libraries": [],
        "methods": [
          "totalSupply()",
          "balanceOf(address)",
          "transfer(address,uint256)",
          "allowance(address,address)",
          "approve(address,uint256)",
          "transferFrom(address,address,uint256)"
        ],
        "linkReferences": [],
        "errors": [],
        "layout": {
          "storage": [],
          "types": {},
          "layoutVersion": "1.1"
        }
      },
      "IERC20Metadata": {
        "src": "@openzeppelin\\contracts\\token\\ERC20\\extensions\\IERC20Metadata.sol:13",
        "inherit": [
          "IERC20"
        ],
        "libraries": [],
        "methods": [
          "name()",
          "symbol()",
          "decimals()"
        ],
        "linkReferences": [],
        "errors": [],
        "layout": {
          "storage": [],
          "types": {},
          "layoutVersion": "1.1"
        }
      },
      "Context": {
        "src": "@openzeppelin\\contracts\\utils\\Context.sol:16",
        "inherit": [],
        "libraries": [],
        "methods": [],
        "linkReferences": [],
        "errors": [],
        "layout": {
          "storage": [],
          "types": {},
          "layoutVersion": "1.1"
        }
      },
      "POTATToken": {
        "src": "contracts\\main.sol:5",
        "version": {
          "withMetadata": "4b8fd72cd24b6fb075c87183dfe3ba4ff8f72ba2121271be3f030c92b0013b60",
          "withoutMetadata": "24f377a9063dc749ce9cfbd43986d50100471615b62b9a9257aca97017ce4d3e",
          "linkedWithoutMetadata": "24f377a9063dc749ce9cfbd43986d50100471615b62b9a9257aca97017ce4d3e"
        },
        "inherit": [
          "ERC20",
          "IERC20Metadata",
          "IERC20",
          "Context"
        ],
        "libraries": [],
        "methods": [
          "()",
          "buying()"
        ],
        "linkReferences": [],
        "errors": [
          {
            "kind": "constructor",
            "contract": "POTATToken",
            "src": "contracts\\main.sol:15"
          }
        ],
        "layout": {
          "storage": [
            {
              "contract": "POTATToken",
              "label": "owner",
              "type": "t_address",
              "src": "contracts\\main.sol:6"
            }
          ],
          "types": {
            "t_address": {
              "label": "address"
            }
          },
          "layoutVersion": "1.1"
        }
      }
    }
  ]
}